wxswutilsapi/AsyncThread.py
wxswutilsapi/__init__.py
wxswutilsapi/check_spec.py
wxswutilsapi/database.py
wxswutilsapi/logger.py
wxswutilsapi/mydb.py
wxswutilsapi/pid.py
wxswutilsapi/pls.py
wxswutilsapi/print.py
wxswutilsapi/proc_data.py
wxswutilsapi/proxy_server.py
wxswutilsapi/pyqt_shell.py
wxswutilsapi/resultBean.py
wxswutilsapi/utils.py
wxswutilsapi/websocket_server.py
wxswutilsapi-0.1.77.dist-info/METADATA
wxswutilsapi-0.1.77.dist-info/WHEEL
wxswutilsapi-0.1.77.dist-info/top_level.txt
wxswutilsapi-0.1.77.dist-info/RECORD
