Metadata-Version: 2.2
Name: wxswutilsapi
Version: 0.1.77
Summary: python 工具库
Author: liudaiyi
Author-email: 121274222@qq.com
Classifier: Programming Language :: Python :: 3
Classifier: License :: OSI Approved :: MIT License
Classifier: Operating System :: OS Independent
Requires-Python: >=3.9
Dynamic: author
Dynamic: author-email
Dynamic: classifier
Dynamic: description
Dynamic: description-content-type
Dynamic: requires-python
Dynamic: summary
